python_ubl-0.1.5.dist-info/licenses/LICENSE
ubl/__init__.py
ubl/__version__.py
ubl/constants.py
ubl/context.py
ubl/exceptions.py
ubl/identifiers/__init__.py
ubl/identifiers/extractor.py
ubl/identifiers/generator.py
ubl/identifiers/peppol_schemes_v9.4.json
ubl/identifiers/schemes_codes.py
ubl/models/__init__.py
ubl/models/aggregate_components.py
ubl/models/basic_components.py
ubl/models/common.py
ubl/models/documents.py
python_ubl-0.1.5.dist-info/METADATA
python_ubl-0.1.5.dist-info/WHEEL
python_ubl-0.1.5.dist-info/top_level.txt
python_ubl-0.1.5.dist-info/RECORD
