Metadata-Version: 2.4
Name: python_ubl
Version: 0.1.5
Summary: Custom Python UBL 2.1 library with PEPPOL BIS Billing 3.0 support
Author-email: LevIT SC <info@levit.be>
License-Expression: MIT
Project-URL: Homepage, https://levit.be
Keywords: ubl,xml,peppol,e-invoicing,en16931
Classifier: Development Status :: 3 - Alpha
Classifier: Intended Audience :: Developers
Classifier: Programming Language :: Python :: 3
Classifier: Programming Language :: Python :: 3.11
Classifier: Programming Language :: Python :: 3.12
Classifier: Programming Language :: Python :: 3.13
Classifier: Topic :: Software Development :: Libraries :: Python Modules
Classifier: Topic :: Office/Business :: Financial
Requires-Python: >=3.11
License-File: LICENSE
Requires-Dist: lxml>=4.9.0
Requires-Dist: python-dateutil>=2.8.0
Provides-Extra: dev
Requires-Dist: pytest>=7.0.0; extra == "dev"
Requires-Dist: pytest-cov>=4.0.0; extra == "dev"
Requires-Dist: ruff>=0.1.0; extra == "dev"
Provides-Extra: django
Requires-Dist: django>=4.2; extra == "django"
Dynamic: license-file
